dbdocs/__init__.py
dbdocs/__main__.py
dbdocs/cli/__init__.py
dbdocs/cli/main.py
dbdocs/helpers/__init__.py
dbdocs/helpers/log.py
dbdocs/main.py
LICENSE
README.md
dbdocs-0.0.1.dist-info/entry_points.txt
dbdocs-0.0.1.dist-info/LICENSE
dbdocs-0.0.1.dist-info/METADATA
dbdocs-0.0.1.dist-info/WHEEL
dbdocs-0.0.1.dist-info/RECORD
