Metadata-Version: 2.1
Name: dbdocs
Version: 0.0.1
Summary: Auto-generated data documentation site for dbt projects
Home-page: https://github.com/datnguye/dbt-docs
License: MIT
Keywords: flake8,markdown,lint
Author: Dat Nguyen
Author-email: datnguyen.it09@gmail.com
Requires-Python: >=3.9,<4.0
Classifier: Environment :: Console
Classifier: License :: OSI Approved :: MIT License
Classifier: Operating System :: OS Independent
Classifier: Programming Language :: Python :: 3
Classifier: Programming Language :: Python :: 3.9
Classifier: Programming Language :: Python :: 3.10
Classifier: Programming Language :: Python :: 3.11
Classifier: Topic :: Software Development :: Documentation
Classifier: Topic :: Software Development :: Libraries :: Python Modules
Classifier: Topic :: Software Development :: Quality Assurance
Requires-Dist: click (>=8.1,<9.0)
Requires-Dist: dbterd (>=1,<2)
Requires-Dist: jinja2 (>=3.1,<4.0)
Project-URL: Repository, https://github.com/datnguye/dbt-docs
